odoo10_addon_test_invader_payment-10.0.2.0.0.99.dev4-py3.8-nspkg.pth
odoo/addons/test_invader_payment/README.rst
odoo/addons/test_invader_payment/__init__.py
odoo/addons/test_invader_payment/__manifest__.py
odoo/addons/test_invader_payment/components/__init__.py
odoo/addons/test_invader_payment/components/payment_transaction_event_listerner.py
odoo/addons/test_invader_payment/i18n/test_invader_payment.pot
odoo/addons/test_invader_payment/models/__init__.py
odoo/addons/test_invader_payment/models/payment_transaction.py
odoo/addons/test_invader_payment/models/res_partner.py
odoo/addons/test_invader_payment/readme/CONTRIBUTORS.rst
odoo/addons/test_invader_payment/readme/DESCRIPTION.rst
odoo/addons/test_invader_payment/services/__init__.py
odoo/addons/test_invader_payment/services/invader_payment_service.py
odoo/addons/test_invader_payment/services/payment_manual.py
odoo/addons/test_invader_payment/services/payment_sips.py
odoo/addons/test_invader_payment/services/payment_stripe.py
odoo/addons/test_invader_payment/static/description/index.html
odoo/addons/test_invader_payment/tests/__init__.py
odoo/addons/test_invader_payment/tests/common.py
odoo/addons/test_invader_payment/tests/test_invader_payment_manual.py
odoo/addons/test_invader_payment/tests/test_invader_payment_sips.py
odoo/addons/test_invader_payment/tests/test_invader_payment_stripe.py
odoo/addons/test_invader_payment/tests/cassettes/TestInvaderPaymentSips.test_prepare_payment.yaml
odoo/addons/test_invader_payment/tests/cassettes/TestInvaderPaymentStripe.test_confirm_payment_one_step.yaml
odoo/addons/test_invader_payment/tests/cassettes/TestInvaderPaymentStripe.test_confirm_payment_two_step.yaml
odoo10_addon_test_invader_payment-10.0.2.0.0.99.dev4.dist-info/METADATA
odoo10_addon_test_invader_payment-10.0.2.0.0.99.dev4.dist-info/WHEEL
odoo10_addon_test_invader_payment-10.0.2.0.0.99.dev4.dist-info/namespace_packages.txt
odoo10_addon_test_invader_payment-10.0.2.0.0.99.dev4.dist-info/top_level.txt
odoo10_addon_test_invader_payment-10.0.2.0.0.99.dev4.dist-info/RECORD
