Metadata-Version: 2.1
Name: odoo10-addon-test-invader-payment
Version: 10.0.2.0.0.99.dev4
Summary: Test Invader payment
Home-page: https://github.com/shopinvader/odoo-shopinvader-payment
Author: Akretion
License: AGPL-3
Platform: UNKNOWN
Classifier: Programming Language :: Python
Classifier: Framework :: Odoo
Classifier: License :: OSI Approved :: GNU Affero General Public License v3
Requires-Python: ~=2.7
Requires-Dist: odoo10-addon-invader-payment-manual
Requires-Dist: odoo10-addon-invader-payment-sips
Requires-Dist: odoo10-addon-invader-payment-stripe
Requires-Dist: odoo (<10.1dev,>=10.0)
